garmentcode/__init__.py
garmentcode/base.py
garmentcode/component.py
garmentcode/connector.py
garmentcode/edge.py
garmentcode/edge_factory.py
garmentcode/interface.py
garmentcode/operators.py
garmentcode/panel.py
garmentcode/params.py
garmentcode/utils.py
mayaqltools/__init__.py
mayaqltools/garmentUI.py
mayaqltools/mayascene.py
mayaqltools/qualothwrapper.py
mayaqltools/scan_imitation.py
mayaqltools/simulation.py
mayaqltools/utils.py
meshgen/__init__.py
meshgen/boxmeshgen.py
meshgen/datasim_utils.py
meshgen/garment.py
meshgen/sim_config.py
meshgen/simulation.py
meshgen/triangulation_utils.py
pattern/__init__.py
pattern/core.py
pattern/rotation.py
pattern/utils.py
pattern/wrappers.py
pygarment-2.0.2.dist-info/licenses/LICENSE
pygarment-2.0.2.dist-info/METADATA
pygarment-2.0.2.dist-info/WHEEL
pygarment-2.0.2.dist-info/top_level.txt
pygarment-2.0.2.dist-info/RECORD
