Metadata-Version: 2.4
Name: pygarment
Version: 2.0.2
Summary: A modular programming framework for designing parametric sewing patterns
Home-page: https://igl.ethz.ch/projects/garmentcode/
Author: Maria Korosteleva
Author-email: maria.korosteleva.public@gmail.com
License: MIT
Project-URL: Bug_Tracker, https://github.com/maria-korosteleva/GarmentCode/issues
Project-URL: repository, https://github.com/maria-korosteleva/GarmentCode
Keywords: garment-programming,garment-modeling,sewing-patterns
Classifier: Programming Language :: Python :: 3
Classifier: Operating System :: OS Independent
Requires-Python: >=3.6
License-File: LICENSE
Requires-Dist: pyyaml>=6.0
Requires-Dist: numpy<2
Requires-Dist: scipy
Requires-Dist: svgwrite
Requires-Dist: svgpathtools
Requires-Dist: psutil
Requires-Dist: matplotlib
Requires-Dist: CairoSVG
Requires-Dist: nicegui
Requires-Dist: trimesh
Requires-Dist: libigl
Requires-Dist: pyrender
Requires-Dist: cgal
Dynamic: license-file
